clairviewanalytics/__init__.py
clairviewanalytics/client.py
clairviewanalytics/consumer.py
clairviewanalytics/exception_capture.py
clairviewanalytics/exception_utils.py
clairviewanalytics/feature_flags.py
clairviewanalytics/poller.py
clairviewanalytics/py.typed
clairviewanalytics/request.py
clairviewanalytics/utils.py
clairviewanalytics/version.py
clairviewanalytics/exception_integrations/__init__.py
clairviewanalytics/exception_integrations/django.py
clairviewanalytics/sentry/__init__.py
clairviewanalytics/sentry/clairview_integration.py
clairviewanalytics/sentry/django.py
clairviewanalytics/test/__init__.py
clairviewanalytics/test/test_client.py
clairviewanalytics/test/test_consumer.py
clairviewanalytics/test/test_exception_capture.py
clairviewanalytics/test/test_feature_flags.py
clairviewanalytics/test/test_module.py
clairviewanalytics/test/test_request.py
clairviewanalytics/test/test_utils.py
clairviewanalytics-3.7.0.dist-info/LICENSE
clairviewanalytics-3.7.0.dist-info/METADATA
clairviewanalytics-3.7.0.dist-info/WHEEL
clairviewanalytics-3.7.0.dist-info/top_level.txt
clairviewanalytics-3.7.0.dist-info/RECORD
